Workbook

Sheet README
A1: Language Risk Audit — Evaluation Input Workbook
A3: Purpose | B3: Create, review and test a five-case pack now; expand the same structure to 25–30 cases later.
A4: Current scope | B4: Indian English, Singapore English and an American English control.
A5: Today’s target | B5: Complete and review IND-01, IND-02, SG-01, SG-02 and US-01.
A6: Important | B6: The three prototype examples are starting material, not validated benchmark items.
A7: Before testing | B7: Write the intended meaning, possible misunderstanding, expected severity and expected recommendation.
A8: After testing | B8: Record the complete output and scores in Test Runs. Do not change the prompt until all five cases are run.
A10: Sheet | B10: How to use it
A11: Case Input | B11: Enter one case per row. Yellow cells are the fields that require team review before testing.
A12: Test Runs | B12: Record one run per case, score six criteria from 0–2, and assign failure labels and priority.
A13: Rubric | B13: Use the shared definitions for scores, failure labels and priorities.
A14: Provenance rule | B14: Never paste confidential messages. Do not copy corpus text unless its licence permits reuse.

Sheet Case Input
A1: Case Input — reference answers must be completed before testing
A2: Case ID | B2: Status | C2: Source variety | D2: Original text | E2: Context | F2: Intended audience | G2: Intended meaning | H2: Possible misunderstanding | I2: Expected severity | J2: Expected recommendation | K2: What the audit must not do | L2: Source type | M2: Source / provenance | N2: Source URL | O2: Reviewer
A3: IND-01 | B3: Needs review | C3: Indian English | D3: Please revert by tomorrow. | E3: Workplace message | F3: International colleague | G3: Please reply by tomorrow. | H3: A reader may understand revert as returning something to an earlier state rather than replying. | I3: Medium | J3: For a broad audience, consider: ‘Please reply by tomorrow.’ | K3: Describe Indian English as incorrect or claim that every reader will misunderstand it. | L3: INTERNAL_DEMO | M3: Current prototype example; linguistic interpretation requires reviewer confirmation.
A4: IND-02 | B4: Needs review | C4: Indian English | D4: Can we prepone the meeting? | E4: Workplace scheduling | F4: International colleague | G4: Can we move the meeting to an earlier time or date? | H4: Prepone may be unfamiliar to readers who do not use Indian English. | I4: Medium | J4: For a broad audience, consider: ‘Can we move the meeting earlier?’ | K4: Treat a locally established word as inherently defective. | L4: INTERNAL_DEMO | M4: Current prototype example; add an external source before treating it as a validated test case.
A5: SG-01 | B5: Needs review | C5: Singapore English | D5: Please send me the document by today, can? | E5: Workplace request | F5: International colleague | G5: The writer is asking whether the recipient can send the document today. | H5: A reader unfamiliar with this use of ‘can’ may find the ending incomplete or unusually abrupt. | I5: Low | J5: Retain it for an audience familiar with this usage; for a broader audience, use: ‘Could you send me the document today?’ | K5: Stereotype Singaporean speakers or automatically mark the sentence as bad English. | L5: INTERNAL_DEMO | M5: Current prototype example; linguistic interpretation requires reviewer confirmation.
A6: SG-02 | B6: Draft
A7: US-01 | B7: Needs review | C7: American English | D7: Please send the revised report by 5 pm tomorrow. | E7: Workplace request | F7: International colleague | G7: Send the revised report no later than 5 pm tomorrow. | H7: No substantial misunderstanding is expected when the date and time zone are shared. | I7: Low | J7: No adaptation is necessary; add a time zone only when recipients are in different locations. | K7: Invent a dialect risk or recommend unnecessary rewriting. | L7: TEAM_CREATED_CONTROL | M7: Team-authored low-risk control case.
A8: SG-03 | B8: Hold | C8: Singapore English | D8: I ever met some customer like that. | E8: Workplace message | F8: International colleague | G8: I have met some customer like that. | I8: High | J8: For a buisness audience - I have met some constomers like that | K8: Describe Singaporean English as incorrect or claim that every reader will misunderstand it. | L8: DOCUMENTED_FEATURE | M8: eWave
A9: CASE-07 | B9: Needs review | C9: Singapore English | D9: John give his boss scold. | E9: General | F9: International colleague | G9: John was scolded by his boss | I9: High | J9: For a broad audience, consider: "John was scolded by his boss" | K9: Describe Singaporean English as incorrect or claim that every reader will misunderstand it. | L9: DOCUMENTED_FEATURE | M9: eWave
A10: CASE-08 | B10: Needs review | C10: Singapore English | D10: Tell me this project is what. | E10: Workplace message | F10: International colleague | G10: Tell me, what is this project? | I10: Medium | L10: DOCUMENTED_FEATURE | M10: eWave
A11: CASE-09 | B11: Draft | C11: Singapore English | D11: So you guys know or not? | E11: General | F11: International colleague | I11: Low | J11: For a buisness audience, so do you guys know? | K11: Stereotype Singaporean speakers or automatically mark the sentence as bad English. | L11: DOCUMENTED_FEATURE | M11: eWave
A12: CASE-10 | B12: Draft | C12: Singapore English | D12: Answer the question, can or not? | E12: Customer Service | F12: International client | G12: Do you know the answer to the question? | I12: Medium | J12: For a broad audience, consider: do you know the answer to the question? | K12: Describe Singaporean English as incorrect or claim that every reader will misunderstand it. | L12: DOCUMENTED_FEATURE | M12: eWave
A13: CASE-11 | B13: Draft | C13: Indian English | D13: Previously we have arranged one gentleman who is running this. | E13: Workplace handover or project management | F13: International colleague | G13: Previously, we appointed or arranged for a particular person to manage this. | H13: “Arranged one gentleman” may be interpreted as organising a meeting with him rather than appointing or obtaining someone to perform the role. | I13: Medium | L13: DOCUMENTED_FEATURE | M13: eWave
A14: CASE-12 | B14: Draft | C14: Indian English | D14: I have come here about six months back. | E14: Workplace introduction or relocation discussion | F14: International colleague | G14: I arrived here approximately six months ago and have probably remained here since then. | H14: The combination of present perfect and “six months back” may leave some readers uncertain whether the speaker is describing arrival, a previous visit or their current residence. | I14: Low | M14: eWave
A15: CASE-13 | B15: Draft | C15: Indian English | D15: I would be visiting your place tomorrow. | E15: Workplace visit or appointment | F15: Colleague or client | G15: The speaker plans or expects to visit the recipient’s location tomorrow. | H15: Some readers may interpret “would be visiting” as conditional, tentative or dependent on an unstated condition rather than as a definite plan. | I15: Medium | M15: eWave
A16: CASE-14 | B16: Needs review | C16: Indian English | D16: They have took more pain for this. | E16: Project acknowledgement or performance discussion | F16: International colleague | G16: The people concerned put considerable effort into completing the task. | H16: A reader may interpret “pain” literally as physical or emotional suffering rather than effort, care or trouble taken. | I16: Medium | M16: eWave
A17: CASE-15 | B17: Draft | C17: Indian English | D17: I can buy ticket on train itself? | E17: Travel-support question | F17: Service or support employee | G17: The speaker is asking whether the ticket can be bought on the train rather than before boarding. | H17: A reader may find “itself” unnecessary or may not recognise that it emphasises the location where the ticket can be purchased. | I17: Low | M17: eWave
A18: CASE-16 | B18: Draft | C18: Indian English | D18: It becomes very clear that what kind of revenues would be there. | E18: Business forecast or investment discussion | F18: International decision-maker | G18: The available information makes the expected type or level of revenue clearer. | H18: The sentence may leave the reader uncertain whether it refers to revenue categories, projected amounts or the existence of revenue. | I18: High | M18: eWave
A19: CASE-17 | B19: Draft | C19: American English | D19: Meet me on the first floor by the elevators. | E19: Office meeting | F19: International colleague | G19: Meet on the ground-level floor of the building, following common American floor numbering. | M19: eWave
A20: CASE-18 | B20: Draft | C20: American English | D20: Let's table the proposal until next week's meeting. | E20: Project meeting | F20: International project team | G20: The speaker intends to postpone discussion of the proposal until next week. | I20: Medium | M20: Generated by Maria and chatGPT
A21: CASE-19 | B21: Draft | C21: American English | D21: Starting in September, the team will meet biweekly. | E21: Team scheduling | F21: International employees | G21: The team will meet either every two weeks or twice each week; the original sentence does not establish which interpretation is intended. | M21: Generated by Maria and chatGPT
A22: CASE-20 | B22: Draft | C22: American English | D22: The customer review is scheduled for 04/05/2026. | E22: Calendar invitation | F22: International colleague | G22: Under the conventional American month/day/year interpretation, the review is scheduled for April 5, 2026. | M22: Generated by Maria and chatGPT
A23: CASE-21 | B23: Draft | C23: American English | D23: Your order has shipped and is expected to arrive on Tuesday. | E23: Customer-support notification | F23: International customer | G23: The order has left the seller and is expected to be delivered on Tuesday. | H23: Little or no meaningful misunderstanding is expected. “Expected” appropriately communicates that Tuesday is an estimate rather than a guarantee. | I23: Low | M23: Generated by Maria and chatGPT
A24: CASE-22 | B24: Draft
A25: CASE-23 | B25: Draft
A26: CASE-24 | B26: Draft
A27: CASE-25 | B27: Draft
A28: CASE-26 | B28: Draft
A29: CASE-27 | B29: Draft
A30: CASE-28 | B30: Draft
A31: CASE-29 | B31: Draft
A32: CASE-30 | B32: Draft

Sheet Sheet2
A1: Case ID | B1: Status | C1: Source variety | D1: Original text | E1: Context | F1: Intended audience | G1: Intended meaning | H1: Possible misunderstanding | I1: Expected severity | J1: Expected recommendation | K1: What the audit must not do | L1: Source type | M1: Source / provenance | N1: Source URL | O1: Reviewer
A2: IND-EW-916 | B2: Needs review | C2: Indian English | D2: Previously we have arranged one gentleman who is running this. | E2: Workplace handover or project management | F2: International colleague | G2: Previously, we appointed or arranged for a particular person to manage this. | H2: “Arranged one gentleman” may be interpreted as organising a meeting with him rather than appointing or obtaining someone to perform the role. | I2: Medium | J2: Clarify the relationship: “We previously appointed someone to manage this” or “We previously arranged for someone to manage this.” | K2: Assume the intended relationship without acknowledging the ambiguity, or describe the expression as simply bad English. | L2: DOCUMENTED_FEATURE | M2: eWAVE Indian English example 916; intended meaning requires contextual confirmation. | N2: https://ewave-atlas.org/sentences/916
A3: IND-EW-925 | B3: Needs review | C3: Indian English | D3: I have come here about six months back. | E3: Workplace introduction or relocation discussion | F3: International colleague | G3: I arrived here approximately six months ago and have probably remained here since then. | H3: The combination of present perfect and “six months back” may leave some readers uncertain whether the speaker is describing arrival, a previous visit or their current residence. | I3: Low | J3: Where the continuing situation matters, consider: “I came here about six months ago and have been here since.” | K3: Claim that “six months back” is incomprehensible or unnecessarily correct it when the meaning is already clear. | L3: DOCUMENTED_FEATURE | M3: eWAVE Indian English example 925; continuing residence is a provisional contextual inference. | N3: https://ewave-atlas.org/sentences/925
A4: IND-EW-929 | B4: Needs review | C4: Indian English | D4: I would be visiting your place tomorrow. | E4: Workplace visit or appointment | F4: Colleague or client | G4: The speaker plans or expects to visit the recipient’s location tomorrow. | H4: Some readers may interpret “would be visiting” as conditional, tentative or dependent on an unstated condition rather than as a definite plan. | I4: Medium | J4: If the visit is confirmed, consider: “I will be visiting your office tomorrow.” If it is tentative, state that explicitly. | K4: Invent an unstated condition or assume that the visit is definitely confirmed without context. | L4: DOCUMENTED_FEATURE | M4: eWAVE Indian English example 929; degree of certainty requires contextual confirmation. | N4: https://ewave-atlas.org/sentences/929
A5: IND-EW-931 | B5: Needs review | C5: Indian English | D5: They have took more pain for this. | E5: Project acknowledgement or performance discussion | F5: International colleague | G5: The people concerned put considerable effort into completing the task. | H5: A reader may interpret “pain” literally as physical or emotional suffering rather than effort, care or trouble taken. | I5: Medium | J5: For a broad workplace audience, consider: “They put a great deal of effort into this” or “They took considerable care over this.” | K5: Focus only on the verb form and miss the possible lexical misunderstanding around “pain.” | L5: DOCUMENTED_FEATURE | M5: eWAVE Indian English example 931; interpretation of “pain” as effort requires reviewer confirmation. | N5: https://ewave-atlas.org/sentences/931
A6: IND-EW-954 | B6: Needs review | C6: Indian English | D6: I can buy ticket on train itself? | E6: Travel-support question | F6: Service or support employee | G6: The speaker is asking whether the ticket can be bought on the train rather than before boarding. | H6: A reader may find “itself” unnecessary or may not recognise that it emphasises the location where the ticket can be purchased. | I6: Low | J6: For a broader audience, consider: “Can I buy a ticket on the train?” Retain the original where this use of “itself” is locally natural and understood. | K6: Treat “itself” as meaningless, describe the speaker negatively or exaggerate a low-risk difference. | L6: DOCUMENTED_FEATURE | M6: eWAVE Indian English example 954; focus interpretation is provisional but strongly supported by the sentence. | N6: https://ewave-atlas.org/sentences/954
A7: Case ID | B7: Status | C7: Source variety | D7: Original text | E7: Context | F7: Intended audience | G7: Intended meaning | H7: Possible misunderstanding | I7: Expected severity | J7: Expected recommendation | K7: What the audit must not do | L7: Source type | M7: Source / provenance | N7: Source URL | O7: Reviewer
A8: US-01 | B8: Needs review | C8: American English | D8: Please send the revised report by 5:00 p.m. Eastern Time on Friday, 28 August 2026. | E8: Workplace deadline | F8: International colleague | G8: Send the revised report by the explicitly stated date, time and time zone. | H8: Little meaningful misunderstanding is expected, although recipients must convert Eastern Time to their local time. | I8: Low | J8: No rewriting is necessary. A local-time equivalent could be added for recipient convenience. | K8: Invent a dialect problem, exaggerate the time-zone burden or recommend unnecessary standardisation. | L8: TEAM_CREATED_CONTROL | M8: Team-authored low-risk control; not taken from a corpus.
A9: US-02 | B9: Needs review | C9: American English | D9: Meet me on the first floor by the elevators. | E9: Office meeting | F9: International colleague | G9: Meet on the ground-level floor of the building, following common American floor numbering. | H9: A recipient using a system in which the first floor is one level above the ground floor may wait on the wrong floor. | I9: High | J9: Use the building’s displayed level number or say: “Meet me on the ground floor by the elevators.” | K9: Assume that one numbering system is universally correct or attribute the misunderstanding to language proficiency. | L9: TEAM_CREATED_SCENARIO | M9: Team-authored scenario based on cross-regional floor-numbering differences; not a corpus quotation.
A10: US-03 | B10: Needs review | C10: American English | D10: Let's table the proposal until next week's meeting. | E10: Project meeting | F10: International project team | G10: The speaker intends to postpone discussion of the proposal until next week. | H10: Some audiences may understand “table the proposal” as formally presenting it for immediate discussion rather than postponing it. | I10: High | J10: Replace the ambiguous expression with: “Let’s postpone discussion of the proposal until next week’s meeting.” | K10: Claim that every American or every non-American interprets “table” identically, or describe either interpretation as incorrect. | L10: TEAM_CREATED_SCENARIO | M10: Team-authored scenario based on contrasting uses of “table”; requires reviewer confirmation for target audiences.
A11: US-04 | B11: Needs review | C11: American English | D11: Starting in September, the team will meet biweekly. | E11: Team scheduling | F11: International employees | G11: The team will meet either every two weeks or twice each week; the original sentence does not establish which interpretation is intended. | H11: “Biweekly” is ambiguous even among American English speakers and could produce incompatible schedules. | I11: High | J11: State the frequency explicitly: “every two weeks” or “twice a week.” | K11: The audit must not pretend to know the intended schedule or incorrectly present this as exclusively a dialect issue. | L11: TEAM_CREATED_SCENARIO | M11: Team-authored general American-English ambiguity; intended frequency deliberately unspecified.
A12: US-05 | B12: Needs review | C12: American English | D12: The customer review is scheduled for 04/05/2026. | E12: Calendar invitation | F12: International colleague | G12: Under the conventional American month/day/year interpretation, the review is scheduled for April 5, 2026. | H12: A reader using day/month/year may interpret the date as 4 May 2026. | I12: High | J12: Write the month in words or use an unambiguous standard: “5 April 2026” or “2026-04-05.” | K12: Guess the date without flagging the ambiguity, or claim that one regional date convention is inherently superior. | L12: TEAM_CREATED_SCENARIO | M12: Team-authored scenario based on regional numeric-date conventions; not a corpus quotation.
A13: US-06 | B13: Needs review | C13: American English | D13: Your order has shipped and is expected to arrive on Tuesday. | E13: Customer-support notification | F13: International customer | G13: The order has left the seller and is expected to be delivered on Tuesday. | H13: Little or no meaningful misunderstanding is expected. “Expected” appropriately communicates that Tuesday is an estimate rather than a guarantee. | I13: Low | J13: Retain the original. Add a tracking link only if one is available. | K13: Invent a dialect-specific problem, treat the estimated date as guaranteed or recommend unnecessary rewriting. | L13: TEAM_CREATED_CONTROL | M13: Team-authored low-risk control; not taken from a corpus.
A18: Case ID | B18: Status | C18: Source variety | D18: Original text | E18: Context | F18: Intended audience | G18: Intended meaning | H18: Possible misunderstanding | I18: Expected severity | J18: Expected recommendation | K18: What the audit must not do | L18: Source type | M18: Source / provenance | N18: Source URL | O18: Reviewer
A19: IND-EW-916 | B19: Needs review | C19: Indian English | D19: Previously we have arranged one gentleman who is running this. | E19: Workplace handover or project management | F19: International colleague | G19: Previously, we appointed or arranged for a particular person to manage this. | H19: “Arranged one gentleman” may be interpreted as organising a meeting with him rather than appointing or obtaining someone to perform the role. | I19: Medium | J19: Clarify the relationship: “We previously appointed someone to manage this” or “We previously arranged for someone to manage this.” | K19: Assume the intended relationship without acknowledging the ambiguity, or describe the expression as simply bad English. | L19: DOCUMENTED_FEATURE | M19: eWAVE Indian English example 916; intended meaning requires contextual confirmation. | N19: https://ewave-atlas.org/sentences/916
A20: IND-EW-925 | B20: Needs review | C20: Indian English | D20: I have come here about six months back. | E20: Workplace introduction or relocation discussion | F20: International colleague | G20: I arrived here approximately six months ago and have probably remained here since then. | H20: The combination of present perfect and “six months back” may leave some readers uncertain whether the speaker is describing arrival, a previous visit or their current residence. | I20: Low | J20: Where the continuing situation matters, consider: “I came here about six months ago and have been here since.” | K20: Claim that “six months back” is incomprehensible or unnecessarily correct it when the meaning is already clear. | L20: DOCUMENTED_FEATURE | M20: eWAVE Indian English example 925; continuing residence is a provisional contextual inference. | N20: https://ewave-atlas.org/sentences/925
A21: IND-EW-929 | B21: Needs review | C21: Indian English | D21: I would be visiting your place tomorrow. | E21: Workplace visit or appointment | F21: Colleague or client | G21: The speaker plans or expects to visit the recipient’s location tomorrow. | H21: Some readers may interpret “would be visiting” as conditional, tentative or dependent on an unstated condition rather than as a definite plan. | I21: Medium | J21: If the visit is confirmed, consider: “I will be visiting your office tomorrow.” If it is tentative, state that explicitly. | K21: Invent an unstated condition or assume that the visit is definitely confirmed without context. | L21: DOCUMENTED_FEATURE | M21: eWAVE Indian English example 929; degree of certainty requires contextual confirmation. | N21: https://ewave-atlas.org/sentences/929
A22: IND-EW-931 | B22: Needs review | C22: Indian English | D22: They have took more pain for this. | E22: Project acknowledgement or performance discussion | F22: International colleague | G22: The people concerned put considerable effort into completing the task. | H22: A reader may interpret “pain” literally as physical or emotional suffering rather than effort, care or trouble taken. | I22: Medium | J22: For a broad workplace audience, consider: “They put a great deal of effort into this” or “They took considerable care over this.” | K22: Focus only on the verb form and miss the possible lexical misunderstanding around “pain.” | L22: DOCUMENTED_FEATURE | M22: eWAVE Indian English example 931; interpretation of “pain” as effort requires reviewer confirmation. | N22: https://ewave-atlas.org/sentences/931
A23: IND-EW-954 | B23: Needs review | C23: Indian English | D23: I can buy ticket on train itself? | E23: Travel-support question | F23: Service or support employee | G23: The speaker is asking whether the ticket can be bought on the train rather than before boarding. | H23: A reader may find “itself” unnecessary or may not recognise that it emphasises the location where the ticket can be purchased. | I23: Low | J23: For a broader audience, consider: “Can I buy a ticket on the train?” Retain the original where this use of “itself” is locally natural and understood. | K23: Treat “itself” as meaningless, describe the speaker negatively or exaggerate a low-risk difference. | L23: DOCUMENTED_FEATURE | M23: eWAVE Indian English example 954; focus interpretation is provisional but strongly supported by the sentence. | N23: https://ewave-atlas.org/sentences/954
A24: IND-EW-955 | B24: Needs review | C24: Indian English | D24: It becomes very clear that what kind of revenues would be there. | E24: Business forecast or investment discussion | F24: International decision-maker | G24: The available information makes the expected type or level of revenue clearer. | H24: The sentence may leave the reader uncertain whether it refers to revenue categories, projected amounts or the existence of revenue. | I24: High | J24: Specify the intended business claim, for example: “This makes the expected revenue streams clear” or “This makes the projected revenue level clear.” | K24: Invent financial details, silently choose between revenue type and amount, or present an uncertain interpretation as fact. | L24: DOCUMENTED_FEATURE | M24: eWAVE Indian English example 955; the precise meaning of “what kind of revenues” requires contextual confirmation. | N24: https://ewave-atlas.org/sentences/955

Sheet Sheet3

Sheet Test Runs
A1: Test Runs — record the complete result before changing the prompt
A2: Scores use 0 = Fail, 1 = Partial, 2 = Pass. Total score is calculated automatically out of 12.
A3: Case ID | B3: Source variety | C3: Original text | D3: Run date | E3: App version / commit | F3: Run completed? | G3: Latency (sec) | H3: Actual result / summary | I3: Meaning | J3: Variety awareness | K3: Risk identification | L3: Non-stereotyping | M3: Recommendation | N3: Confidence | O3: Total / 12 | P3: Failure labels | Q3: Priority | R3: Print / PDF | S3: Screenshot / result link | T3: Problems / notes | U3: Owner | V3: Retest status
A4: ='Case Input'!A3 -> IND-01 | B4: ='Case Input'!C3 -> Indian English | C4: ='Case Input'!D3 -> Please revert by tomorrow. | O4: =IF(COUNT(I4:N4)=0,"",SUM(I4:N4))
A5: ='Case Input'!A4 -> IND-02 | B5: ='Case Input'!C4 -> Indian English | C5: ='Case Input'!D4 -> Can we prepone the meeting? | O5: =IF(COUNT(I5:N5)=0,"",SUM(I5:N5))
A6: ='Case Input'!A5 -> SG-01 | B6: ='Case Input'!C5 -> Singapore English | C6: ='Case Input'!D5 -> Please send me the document by today, can? | O6: =IF(COUNT(I6:N6)=0,"",SUM(I6:N6))
A7: ='Case Input'!A6 -> SG-02 | B7: ='Case Input'!C6 -> 0 | C7: ='Case Input'!D6 -> 0 | O7: =IF(COUNT(I7:N7)=0,"",SUM(I7:N7))
A8: ='Case Input'!A7 -> US-01 | B8: ='Case Input'!C7 -> American English | C8: ='Case Input'!D7 -> Please send the revised report by 5 pm tomorrow. | O8: =IF(COUNT(I8:N8)=0,"",SUM(I8:N8))
A9: ='Case Input'!A8 -> SG-03 | B9: ='Case Input'!C8 -> Singapore English | C9: ='Case Input'!D8 -> I ever met some customer like that. | O9: =IF(COUNT(I9:N9)=0,"",SUM(I9:N9))
A10: ='Case Input'!A9 -> CASE-07 | B10: ='Case Input'!C9 -> Singapore English | C10: ='Case Input'!D9 -> John give his boss scold. | O10: =IF(COUNT(I10:N10)=0,"",SUM(I10:N10))
A11: ='Case Input'!A10 -> CASE-08 | B11: ='Case Input'!C10 -> Singapore English | C11: ='Case Input'!D10 -> Tell me this project is what. | O11: =IF(COUNT(I11:N11)=0,"",SUM(I11:N11))
A12: ='Case Input'!A11 -> CASE-09 | B12: ='Case Input'!C11 -> Singapore English | C12: ='Case Input'!D11 -> So you guys know or not? | O12: =IF(COUNT(I12:N12)=0,"",SUM(I12:N12))
A13: ='Case Input'!A12 -> CASE-10 | B13: ='Case Input'!C12 -> Singapore English | C13: ='Case Input'!D12 -> Answer the question, can or not? | O13: =IF(COUNT(I13:N13)=0,"",SUM(I13:N13))
A14: ='Case Input'!A13 -> CASE-11 | B14: ='Case Input'!C13 -> Indian English | C14: ='Case Input'!D13 -> Previously we have arranged one gentleman who is running this. | O14: =IF(COUNT(I14:N14)=0,"",SUM(I14:N14))
A15: ='Case Input'!A14 -> CASE-12 | B15: ='Case Input'!C14 -> Indian English | C15: ='Case Input'!D14 -> I have come here about six months back. | O15: =IF(COUNT(I15:N15)=0,"",SUM(I15:N15))
... A33: ='Case Input'!A32 -> CASE-30 | B33: ='Case Input'!C32 -> 0 | C33: ='Case Input'!D32 -> 0 | O33: =IF(COUNT(I33:N33)=0,"",SUM(I33:N33))

Sheet Rubric
A1: Evaluation Rubric and Failure Labels
A3: Criterion | B3: 0 — Fail | C3: 1 — Partial | D3: 2 — Pass
A4: Meaning | B4: Misunderstands the text | C4: Partly understands it | D4: Accurately explains it
A5: Variety awareness | B5: Wrong or absent | C5: Recognises some features | D5: Handles the variety accurately
A6: Risk identification | B6: Misses or invents risk | C6: Broadly correct but vague | D6: Identifies the actual communication gap
A7: Non-stereotyping | B7: Uses stereotypes or deficit language | C7: Some questionable generalisation | D7: Careful, contextual and respectful
A8: Recommendation | B8: Harmful or unnecessary correction | C8: Generic advice | D8: Specific, proportionate and useful
A9: Confidence | B9: Presents guesses as facts | C9: Some qualification | D9: Distinguishes evidence from uncertainty
A12: Failure label | B12: Meaning
A13: MISSED_RISK | B13: A genuine communication problem was not identified
A14: FALSE_ALARM | B14: A harmless feature was treated as risky
A15: MEANING_ERROR | B15: The text was misunderstood
A16: VARIETY_ERROR | B16: The English variety was misidentified or mishandled
A17: STEREOTYPE | B17: The explanation relied on cultural or linguistic stereotypes
A18: DEFICIT_FRAMING | B18: Legitimate variation was described as bad English
A19: VAGUE_ADVICE | B19: The recommendation was too generic to use
A20: OVER_CORRECTION | B20: The tool unnecessarily standardised the language
A21: SCORE_MISMATCH | B21: The numerical result contradicted the explanation
A22: TECHNICAL_FAILURE | B22: The workflow, deployment or download failed
A23: UNCLEAR_UI | B23: The content existed but was difficult to understand
A26: Priority | B26: Meaning | C26: Action
A27: P0 | B27: Product or demo cannot run | C27: Fix immediately
A28: P1 | B28: Serious content error, stereotyping or broken audit output | C28: Fix before public V0
A29: P2 | B29: Confusing wording or non-critical interface problem | C29: Fix if time permits
A30: P3 | B30: Cosmetic detail | C30: Leave until after V0
A33: Reference-answer field | B33: Question to answer before running the app
A34: Intended meaning | B34: What does the writer mean in this context?
A35: Potential communication gap | B35: What might an unfamiliar audience misunderstand?
A36: Risk level | B36: Low, medium or high — and why?
A37: Appropriate recommendation | B37: Retain locally, explain, or adapt for a broader audience?
A38: Must not do | B38: What stereotyping, deficit framing or false certainty must the audit avoid?
A39: Provenance | B39: Where did the example or documented feature come from?

Sheet Raw
A1: Candidate ID | B1: eWAVE ID | C1: Test-ready text | D1: Raw eWAVE example | E1: Variety | F1: Variety type | G1: Source type | H1: Source URL | I1: Review status
A2: SG-EW-3580 | B2: 3580 | C2: So you guys know or not? | D2: So you guys know or not? | E2: Colloquial Singapore English (Singlish) | F2: High-contact L1 variety | G2: DOCUMENTED_FEATURE | H2: https://ewave-atlas.org/sentences/3580 | I2: Unreviewed
A3: SG-EW-3581 | B3: 3581 | C3: I got from the career fax. | D3: I got Ø from the career fax. | E3: Colloquial Singapore English (Singlish) | F3: High-contact L1 variety | G3: DOCUMENTED_FEATURE | H3: https://ewave-atlas.org/sentences/3581 | I3: Needs context
A4: SG-EW-3582 | B4: 3582 | C4: I go in about hour earlier, come back hour later or something. | D4: I go in about hour earlier, Ø come back hour later or something. | E4: Colloquial Singapore English (Singlish) | F4: High-contact L1 variety | G4: DOCUMENTED_FEATURE | H4: https://ewave-atlas.org/sentences/3582 | I4: Unreviewed
A5: SG-EW-3583 | B5: 3583 | C5: Sometime difficult to say eh. | D5: Sometime Ø difficult to say eh. | E5: Colloquial Singapore English (Singlish) | F5: High-contact L1 variety | G5: DOCUMENTED_FEATURE | H5: https://ewave-atlas.org/sentences/3583 | I5: Unreviewed
A6: SG-EW-3584 | B6: 3584 | C6: So I bought a lot of furnitures from IKEA. | D6: So I bought a lot of furnitures from IKEA. | E6: Colloquial Singapore English (Singlish) | F6: High-contact L1 variety | G6: DOCUMENTED_FEATURE | H6: https://ewave-atlas.org/sentences/3584 | I6: Unreviewed
A7: SG-EW-3585 | B7: 3585 | C7: A lot of churches design webpage. | D7: A lot of churches design webpage. | E7: Colloquial Singapore English (Singlish) | F7: High-contact L1 variety | G7: DOCUMENTED_FEATURE | H7: https://ewave-atlas.org/sentences/3585 | I7: Unreviewed
A8: SG-EW-3586 | B8: 3586 | C8: That was first time I did promise them. | D8: That was Ø first time I did promise them. | E8: Colloquial Singapore English (Singlish) | F8: High-contact L1 variety | G8: DOCUMENTED_FEATURE | H8: https://ewave-atlas.org/sentences/3586 | I8: Unreviewed
A9: SG-EW-3587 | B9: 3587 | C9: And got to know this kind-hearted scholar who shelter her with umbrella when it was raining. | D9: And got to know this kind-hearted scholar who shelter her with Ø umbrella when it was raining. | E9: Colloquial Singapore English (Singlish) | F9: High-contact L1 variety | G9: DOCUMENTED_FEATURE | H9: https://ewave-atlas.org/sentences/3587 | I9: Unreviewed
A10: SG-EW-3588 | B10: 3588 | C10: They sold already ah? | D10: They sold already ah? | E10: Colloquial Singapore English (Singlish) | F10: High-contact L1 variety | G10: DOCUMENTED_FEATURE | H10: https://ewave-atlas.org/sentences/3588 | I10: Unreviewed
A11: SG-EW-3589 | B11: 3589 | C11: I ever met some customer like that. | D11: I ever met some customer like that. | E11: Colloquial Singapore English (Singlish) | F11: High-contact L1 variety | G11: DOCUMENTED_FEATURE | H11: https://ewave-atlas.org/sentences/3589 | I11: Unreviewed
A12: SG-EW-3590A | B12: 3590 | C12: I have eaten already. | D12: I have eaten/ eat/ got eat already. | E12: Colloquial Singapore English (Singlish) | F12: High-contact L1 variety | G12: DOCUMENTED_FEATURE | H12: https://ewave-atlas.org/sentences/3590 | I12: Split from alternatives
A13: SG-EW-3590B | B13: 3590 | C13: I eat already. | D13: I have eaten/ eat/ got eat already. | E13: Colloquial Singapore English (Singlish) | F13: High-contact L1 variety | G13: DOCUMENTED_FEATURE | H13: https://ewave-atlas.org/sentences/3590 | I13: Split from alternatives
... A105: IND-EW-957 | B105: 957 | C105: I was like what the hell are you trying to do? | D105: I was like what the hell are you trying to do? | E105: Indian English | F105: Indigenized L2 variety | G105: DOCUMENTED_FEATURE | H105: https://ewave-atlas.org/sentences/957 | I105: Useful non-exclusive-feature control
